FPGA_project/week5/week5.srcs/sources_1/new/seg_decoder.v
`timescale 1ns / 1ps
//////////////////////////////////////////////////////////////////////////////////
// Company: 
// Engineer: 
// 
// Create Date: 2025/10/01 17:48:37
// Design Name: 
// Module Name: seg_decoder
// Project Name: 
// Target Devices: 
// Tool Versions: 
// Description: 
// 
// Dependencies: 
// 
// Revision:
// Revision 0.01 - File Created
// Additional Comments:
// 
//////////////////////////////////////////////////////////////////////////////////


module seg_decoder(
    input   wire    [3:0]   i_digit,
    output  reg     [6:0]   o_ca
);

always @(*) begin
    case(i_digit)
        4'd0 : o_ca = 7'b1000000;
        4'd1 : o_ca = 7'b1111001;
        4'd2 : o_ca = 7'b0100100;
        4'd3 : o_ca = 7'b0110000;
        4'd4 : o_ca = 7'b0011001;
        4'd5 : o_ca = 7'b0010010;
        4'd6 : o_ca = 7'b0000010;
        4'd7 : o_ca = 7'b1111000;
        4'd8 : o_ca = 7'b0000000;
        4'd9 : o_ca = 7'b0010000;
        //default : o_ca = 7'b1111111;
    endcase
end
endmodule

FPGA_project/week11/week11.srcs/sources_1/new/week11.v
`timescale 1ns / 1ps
//////////////////////////////////////////////////////////////////////////////////
// Company: 
// Engineer: 
// 
// Create Date: 2025/11/19 15:33:08
// Design Name: 
// Module Name: week11
// Project Name: 
// Target Devices: 
// Tool Versions: 
// Description: 
// 
// Dependencies: 
// 
// Revision:
// Revision 0.01 - File Created
// Additional Comments:
// 
//////////////////////////////////////////////////////////////////////////////////


//module week11(
//    input    wire            i_clk,
//    input    wire            i_rst_n,
//    input    wire            i_btn,
//    output   wire    [7:0]   o_seg,
//    output   wire    [7:0]   o_an
//);

//assign o_an = 8'b1111_1110;

////------------------------------------------------------
//// 1) 버튼 입력 동기화 (2플립플롭)
////------------------------------------------------------
//reg r_btn_sync0;
//reg r_btn_sync1;

//always @(posedge i_clk or negedge i_rst_n)
//begin
//    if(~i_rst_n) begin
//        r_btn_sync0 <= 1'b0;
//        r_btn_sync1 <= 1'b0;
//    end
//    else begin
//        r_btn_sync0 <= i_btn;
//        r_btn_sync1 <= r_btn_sync0;
//    end
//end

////------------------------------------------------------
//// 2) 디바운싱 로직
////    r_btn_sync1 이 일정 시간 이상 유지될 때만 r_btn_db 갱신
////------------------------------------------------------
//parameter TIMEOUT = 1_000_000;   // 클럭 주파수에 맞게 조정 (예: 50MHz 기준 약 20ms 정도)

//reg [19:0] r_db_cnt;
//reg        r_btn_db;

//always @(posedge i_clk or negedge i_rst_n)
//begin
//    if(~i_rst_n) begin
//        r_db_cnt  <= 20'd0;
//        r_btn_db  <= 1'b0;
//    end
//    else begin
//        if (r_btn_sync1 == r_btn_db) begin
//            // 입력과 현재 안정 상태가 같으면 카운터 리셋
//            r_db_cnt <= 20'd0;
//        end
//        else begin
//            // 입력과 현재 안정 상태가 다르면 카운터 동작
//            if (r_db_cnt == TIMEOUT-1) begin
//                r_btn_db <= r_btn_sync1;     // 충분히 오래 유지되면 상태 갱신
//                r_db_cnt <= 20'd0;
//            end
//            else begin
//                r_db_cnt <= r_db_cnt + 1'b1;
//            end
//        end
//    end
//end

////------------------------------------------------------
//// 3) 디바운스된 버튼을 한 사이클 지연
////------------------------------------------------------
//reg r_btn_dly; 

//always @(posedge i_clk or negedge i_rst_n)
//begin
//    if(~i_rst_n)
//        r_btn_dly <= 1'b0;
//    else
//        r_btn_dly <= r_btn_db;   // ★ 여기서 이제 i_btn 대신 r_btn_db 사용
//end

////------------------------------------------------------
//// 4) 상승엣지 검출 (디바운스된 버튼 기준)
////------------------------------------------------------
//wire w_btn_posedge;
//assign w_btn_posedge = r_btn_db & ~r_btn_dly;   // 디바운스된 신호의 상승엣지

////------------------------------------------------------
//// 5) 0~9 카운트
////------------------------------------------------------
//reg [3:0] r_cnt;
//always @(posedge i_clk or negedge i_rst_n)
//begin
//    if(~i_rst_n)
//        r_cnt <= 4'd0;
//    else begin
//        if(w_btn_posedge) begin
//            if(r_cnt == 4'd9)
//                r_cnt <= 4'd0;
//            else
//                r_cnt <= r_cnt + 4'd1;
//        end
//    end
//end

////------------------------------------------------------
//// 6) 세그먼트 출력
////------------------------------------------------------
//wire [6:0] w_ca;

//seg_decoder uut(
//    .i_digit    (r_cnt  ),
//    .o_ca       (w_ca   )
//);

//assign o_seg = {1'b1, w_ca};

//endmodule

//////////////////////////////////////////////////////////////////////////

//module week11(
//    input    wire            i_clk,
//    input    wire            i_rst_n,
//    input    wire            i_btn,
//    output   wire    [7:0]   o_seg,
//    output   wire    [7:0]   o_an
//);

//assign o_an = 8'b1111_1110;

////------------------------------------------------------
//// 디바운싱 (동기화 FF 없이 바로 i_btn 사용)
//// 100MHz 기준 50ms → 5,000,000 클럭
////------------------------------------------------------
//parameter integer TIMEOUT = 2_500_000;

//reg [22:0] r_db_cnt;                                        // 디바운스 카운터
//reg        r_btn_db;                                        // 디바운스된 버튼 값

//always @(posedge i_clk or negedge i_rst_n)
//begin
//    if (~i_rst_n) begin
//        r_db_cnt  <= 23'd0;
//        r_btn_db  <= 1'b0;
//    end
//    else begin
//        if (i_btn == r_btn_db) begin                        // 입력과 현재 확정된 값이 같으면 카운터 리셋
//            r_db_cnt <= 23'd0;
//        end
//        else begin                                          // 입력이 바뀐 것처럼 보이면 일정 시간(50ms) 동안 유지되는지 확인
//            if (r_db_cnt == TIMEOUT - 1) begin
//                r_btn_db <= i_btn;                          // 50ms 동안 계속 같으면 새 값으로 확정
//                r_db_cnt <= 23'd0;
//            end
//            else begin
//                r_db_cnt <= r_db_cnt + 1'b1;
//            end
//        end
//    end
//end

////------------------------------------------------------
//// 디바운스된 버튼을 한 클럭 지연
////------------------------------------------------------
//reg     r_btn_dly;

//always @(posedge i_clk or negedge i_rst_n)
//begin
//    if(~i_rst_n)
//        r_btn_dly <= 1'b0;
//    else
//        r_btn_dly <= r_btn_db;                                  // 이제 i_btn 말고 r_btn_db 사용
//end

////------------------------------------------------------
//// 상승 엣지 검출 (디바운스된 버튼 기준)
////------------------------------------------------------
//wire    w_btn_posedge;
//assign  w_btn_posedge = r_btn_db & ~r_btn_dly;

////------------------------------------------------------
//// 0~9까지 카운트
////------------------------------------------------------
//reg     [3:0]   r_cnt;
//always @(posedge i_clk or negedge i_rst_n)
//begin
//    if(~i_rst_n)
//        r_cnt <= 4'd0;
//    else begin
//        if(w_btn_posedge == 1'b1) begin
//            if(r_cnt == 4'd9)
//                r_cnt <= 4'd0;
//            else
//                r_cnt <= r_cnt + 4'd1;
//        end
//    end
//end

////------------------------------------------------------
//// 세그먼트 디코더
////------------------------------------------------------
//wire    [6:0]   w_ca;

//seg_decoder uut(
//    .i_digit    (r_cnt  ),
//    .o_ca       (w_ca   )
//);

//assign  o_seg = {1'b1, w_ca};   // dot 끔 + 7세그

//endmodule

// 버튼 제어하기 3(교수님)
module week11(
    input    wire            i_clk,
    input    wire            i_rst_n,
    input    wire            i_btn,
    output   wire    [7:0]   o_seg,
    output   wire    [7:0]   o_an
);

//지연된 버튼
assign o_an = 8'b1111_1110;

localparam DEBOUNCE_TIMEOUT     = 24'd20;

reg     r_deb_btn;
reg     [23:0]  r_deb_cnt;

always @(posedge i_clk or negedge i_rst_n)
begin
    if(~i_rst_n)
        r_deb_btn <= 0;
    else
    begin
        if(r_deb_cnt >= DEBOUNCE_TIMEOUT)
            r_deb_btn <= i_btn;
    end
end

always @(posedge i_clk or negedge i_rst_n)
begin
    if(~i_rst_n)
        r_deb_cnt <= 0;
    else begin
        if(i_btn != r_deb_btn)
            r_deb_cnt <= r_deb_cnt + 1;
        else
        r_deb_cnt <= 0;
    end
end

reg     r_btn_dly;                                             //지연된 버튼
always @(posedge i_clk or negedge i_rst_n)
begin
    if(~i_rst_n)
        r_btn_dly <= 0;
    else
        r_btn_dly <= r_deb_btn;
end

//버튼 상승엣지(버튼 누른 순간)
wire    w_btn_posedge;
//assign  w_btn__posedge = (r_deb_btn == 1) & r_btn_dly == 0);        // r_deb_btn이 1, r_btn_dly 가 0인 부분만 1로 만듬
assign  w_btn_posedge = r_deb_btn & ~r_btn_dly;                      // 두 코드가 같은 수행을 함

// 0~9까지 카운트
reg     [3:0]   r_cnt;
always @(posedge i_clk or negedge i_rst_n)
begin
    if(~i_rst_n)
        r_cnt <= 0;
    else
    begin
        if(w_btn_posedge == 1)
        begin
            if(r_cnt == 9)
                r_cnt <= 0;
            else
                r_cnt <= r_cnt + 1;
        end
    end
end

// 카운트 된 값 seg_decoder에서 결과 가져옴
wire        [6:0]   w_ca;
seg_decoder uut(
    .i_digit    (r_cnt      ),
    .o_ca       (w_ca       )
);
assign  o_seg = {1'b1, w_ca};                               // w_ca의 7비트와 dot을 끄는 1비트를 합쳐 8비트로 만들어 출력
endmodule

FPGA_project/week11/week11.srcs/sim_1/new/tb_week11.v
`timescale 1ns / 1ps
//////////////////////////////////////////////////////////////////////////////////
// Company: 
// Engineer: 
// 
// Create Date: 2025/11/23 09:41:25
// Design Name: 
// Module Name: tb_week11
// Project Name: 
// Target Devices: 
// Tool Versions: 
// Description: 
// 
// Dependencies: 
// 
// Revision:
// Revision 0.01 - File Created
// Additional Comments:
// 
//////////////////////////////////////////////////////////////////////////////////

module tb_week11;

    reg         i_clk;
    reg         i_rst_n;
    reg         i_btn;
    wire [7:0]  o_seg;
    wire [7:0]  o_an;

    // DUT
    week11 dut (
        .i_clk   (i_clk),
        .i_rst_n (i_rst_n),
        .i_btn   (i_btn),
        .o_seg   (o_seg),
        .o_an    (o_an)
    );

    // 100 MHz 클럭 (10 ns)
    initial begin
        i_clk = 0;
        forever #5 i_clk = ~i_clk;
    end

    initial begin
        // 초기값
        i_rst_n = 0;
        i_btn   = 0;

        // 리셋 해제
        #100;
        i_rst_n = 1;

        // --- 1번째 버튼 눌림 : 바운싱 구간 ---
        #500;
        repeat(10) begin
            #40;
            i_btn = ~i_btn;    // 0/1 빠르게 토글 → 바운싱 흉내
        end

        // 안정적으로 HIGH 유지 (진짜 눌린 상태)
        i_btn = 1;
        #500;

        // --- 1번째 버튼 뗌 : 바운싱 구간 ---
        repeat(10) begin
            #40;
            i_btn = ~i_btn;
        end

        // 안정적으로 LOW 유지 (완전히 뗀 상태)
        i_btn = 0;
        #100_0;

        // 시뮬레이션 종료
        #1000;
        $finish;
    end

    // 파형 확인용 (필요 없으면 이것도 지워도 됨)
    initial begin
        $dumpfile("week11_tb.vcd");
        $dumpvars(0, tb_week11);
    end

endmodule

FPGA_project/week11/week11.sim/sim_1/behav/xsim/week11_tb.vcd
$date
   Sun Nov 23 09:51:41 2025
$end
$version
  2022.1
$end
$timescale
  1ps
$end
$scope module tb_week11 $end
$var reg 1 ! i_clk $end
$var reg 1 " i_rst_n $end
$var reg 1 # i_btn $end
$var wire 8 $ o_seg [7:0] $end
$var wire 8 % o_an [7:0] $end
$scope module dut $end
$var wire 1 & i_clk $end
$var wire 1 ' i_rst_n $end
$var wire 1 ( i_btn $end
$var wire 8 $ o_seg [7:0] $end
$var wire 8 % o_an [7:0] $end
$var reg 1 ) r_deb_btn $end
$var reg 24 * r_deb_cnt [23:0] $end
$var reg 1 + r_btn_dly $end
$var wire 1 , w_btn_posedge $end
$var reg 4 - r_cnt [3:0] $end
$var wire 7 . w_ca [6:0] $end
$scope module uut $end
$var wire 4 / i_digit [3:0] $end
$var reg 7 0 o_ca [6:0] $end
$upscope $end
$upscope $end
$upscope $end
$enddefinitions $end
#0
$dumpvars
0!
0"
0#
b11000000 $
b11111110 %
0&
0'
0(
0)
b0 *
0+
0,
b0 -
b1000000 .
b0 /
b1000000 0
$end
#5000
1!
1&
#10000
0!
0&
#15000
1!
1&
#20000
0!
0&
#25000
1!
1&
#30000
0!
0&
#35000
1!
1&
#40000
0!
0&
#45000
1!
1&
#50000
0!
0&
#55000
1!
1&
#60000
0!
0&
#65000
1!
1&
#70000
0!
0&
#75000
1!
1&
#80000
0!
0&
#85000
1!
1&
#90000
0!
0&
#95000
1!
1&
#100000
0!
1"
0&
1'
#105000
1!
1&
#110000
0!
0&
#115000
1!
1&
#120000
0!
0&
#125000
1!
1&
#130000
0!
0&
#135000
1!
1&
#140000
0!
0&
#145000
1!
1&
#150000
0!
0&
#155000
1!
1&
#160000
0!
0&
#165000
1!
1&
#170000
0!
0&
#175000
1!
1&
#180000
0!
0&
#185000
1!
1&
#190000
0!
0&
#195000
1!
1&
#200000
0!
0&
#205000
1!
1&
#210000
0!
0&
#215000
1!
1&
#220000
0!
0&
#225000
1!
1&
#230000
0!
0&
#235000
1!
1&
#240000
0!
0&
#245000
1!
1&
#250000
0!
0&
#255000
1!
1&
#260000
0!
0&
#265000
1!
1&
#270000
0!
0&
#275000
1!
1&
#280000
0!
0&
#285000
1!
1&
#290000
0!
0&
#295000
1!
1&
#300000
0!
0&
#305000
1!
1&
#310000
0!
0&
#315000
1!
1&
#320000
0!
0&
#325000
1!
1&
#330000
0!
0&
#335000
1!
1&
#340000
0!
0&
#345000
1!
1&
#350000
0!
0&
#355000
1!
1&
#360000
0!
0&
#365000
1!
1&
#370000
0!
0&
#375000
1!
1&
#380000
0!
0&
#385000
1!
1&
#390000
0!
0&
#395000
1!
1&
#400000
0!
0&
#405000
1!
1&
#410000
0!
0&
#415000
1!
1&
#420000
0!
0&
#425000
1!
1&
#430000
0!
0&
#435000
1!
1&
#440000
0!
0&
#445000
1!
1&
#450000
0!
0&
#455000
1!
1&
#460000
0!
0&
#465000
1!
1&
#470000
0!
0&
#475000
1!
1&
#480000
0!
0&
#485000
1!
1&
#490000
0!
0&
#495000
1!
1&
#500000
0!
0&
#505000
1!
1&
#510000
0!
0&
#515000
1!
1&
#520000
0!
0&
#525000
1!
1&
#530000
0!
0&
#535000
1!
1&
#540000
0!
0&
#545000
1!
1&
#550000
0!
0&
#555000
1!
1&
#560000
0!
0&
#565000
1!
1&
#570000
0!
0&
#575000
1!
1&
#580000
0!
0&
#585000
1!
1&
#590000
0!
0&
#595000
1!
1&
#600000
0!
0&
#605000
1!
1&
#610000
0!
0&
#615000
1!
1&
#620000
0!
0&
#625000
1!
1&
#630000
0!
0&
#635000
1!
1&
#640000
0!
1#
0&
1(
#645000
1!
1&
b1 *
#650000
0!
0&
#655000
1!
1&
b10 *
#660000
0!
0&
#665000
1!
1&
b11 *
#670000
0!
0&
#675000
1!
1&
b100 *
#680000
0!
0#
0&
0(
#685000
1!
1&
b0 *
#690000
0!
0&
#695000
1!
1&
#700000
0!
0&
#705000
1!
1&
#710000
0!
0&
#715000
1!
1&
#720000
0!
1#
0&
1(
#725000
1!
1&
b1 *
#730000
0!
0&
#735000
1!
1&
b10 *
#740000
0!
0&
#745000
1!
1&
b11 *
#750000
0!
0&
#755000
1!
1&
b100 *
#760000
0!
0#
0&
0(
#765000
1!
1&
b0 *
#770000
0!
0&
#775000
1!
1&
#780000
0!
0&
#785000
1!
1&
#790000
0!
0&
#795000
1!
1&
#800000
0!
1#
0&
1(
#805000
1!
1&
b1 *
#810000
0!
0&
#815000
1!
1&
b10 *
#820000
0!
0&
#825000
1!
1&
b11 *
#830000
0!
0&
#835000
1!
1&
b100 *
#840000
0!
0#
0&
0(
#845000
1!
1&
b0 *
#850000
0!
0&
#855000
1!
1&
#860000
0!
0&
#865000
1!
1&
#870000
0!
0&
#875000
1!
1&
#880000
0!
1#
0&
1(
#885000
1!
1&
b1 *
#890000
0!
0&
#895000
1!
1&
b10 *
#900000
0!
0&
#905000
1!
1&
b11 *
#910000
0!
0&
#915000
1!
1&
b100 *
#920000
0!
0#
0&
0(
#925000
1!
1&
b0 *
#930000
0!
0&
#935000
1!
1&
#940000
0!
0&
#945000
1!
1&
#950000
0!
0&
#955000
1!
1&
#960000
0!
1#
0&
1(
#965000
1!
1&
b1 *
#970000
0!
0&
#975000
1!
1&
b10 *
#980000
0!
0&
#985000
1!
1&
b11 *
#990000
0!
0&
#995000
1!
1&
b100 *
#1000000
0!
1#
0&
#1005000
1!
1&
b101 *
#1010000
0!
0&
#1015000
1!
1&
b110 *
#1020000
0!
0&
#1025000
1!
1&
b111 *
#1030000
0!
0&
#1035000
1!
1&
b1000 *
#1040000
0!
0&
#1045000
1!
1&
b1001 *
#1050000
0!
0&
#1055000
1!
1&
b1010 *
#1060000
0!
0&
#1065000
1!
1&
b1011 *
#1070000
0!
0&
#1075000
1!
1&
b1100 *
#1080000
0!
0&
#1085000
1!
1&
b1101 *
#1090000
0!
0&
#1095000
1!
1&
b1110 *
#1100000
0!
0&
#1105000
1!
1&
b1111 *
#1110000
0!
0&
#1115000
1!
1&
b10000 *
#1120000
0!
0&
#1125000
1!
1&
b10001 *
#1130000
0!
0&
#1135000
1!
1&
b10010 *
#1140000
0!
0&
#1145000
1!
1&
b10011 *
#1150000
0!
0&
#1155000
1!
1&
b10100 *
#1160000
0!
0&
#1165000
1!
1&
1)
b10101 *
1,
#1170000
0!
0&
#1175000
1!
b11111001 $
1&
b0 *
1+
0,
b1 -
b1111001 .
b1 /
b1111001 0
