FPGA_project/week5/week5.srcs/sources_1/new/seg_decoder.v
`timescale 1ns / 1ps
//////////////////////////////////////////////////////////////////////////////////
// Company: 
// Engineer: 
// 
// Create Date: 2025/10/01 17:48:37
// Design Name: 
// Module Name: seg_decoder
// Project Name: 
// Target Devices: 
// Tool Versions: 
// Description: 
// 
// Dependencies: 
// 
// Revision:
// Revision 0.01 - File Created
// Additional Comments:
// 
//////////////////////////////////////////////////////////////////////////////////


module seg_decoder(
    input   wire    [3:0]   i_digit,
    output  reg     [6:0]   o_ca
);

always @(*) begin
    case(i_digit)
        4'd0 : o_ca = 7'b1000000;
        4'd1 : o_ca = 7'b1111001;
        4'd2 : o_ca = 7'b0100100;
        4'd3 : o_ca = 7'b0110000;
        4'd4 : o_ca = 7'b0011001;
        4'd5 : o_ca = 7'b0010010;
        4'd6 : o_ca = 7'b0000010;
        4'd7 : o_ca = 7'b1111000;
        4'd8 : o_ca = 7'b0000000;
        4'd9 : o_ca = 7'b0010000;
        //default : o_ca = 7'b1111111;
    endcase
end
endmodule

FPGA_project/week10/week10.srcs/sources_1/new/week10.v
`timescale 1ns / 1ps
//////////////////////////////////////////////////////////////////////////////////
// Company: 
// Engineer: 
// 
// Create Date: 2025/11/12 15:30:45
// Design Name: 
// Module Name: week10
// Project Name: 
// Target Devices: 
// Tool Versions: 
// Description: 
// 
// Dependencies: 
// 
// Revision:
// Revision 0.01 - File Created
// Additional Comments:
// 
//////////////////////////////////////////////////////////////////////////////////

////버튼 제어하기 1
//module week10(
//    input   wire    i_clk,
//    input   wire    i_rst_n,
//    input   wire    i_btn,
//    output  reg     o_led
//    );
    
//// --- 내부 레지스터 선언 ---
//    reg [1:0]  r_btn_sync;       // 1. 동기화를 위한 레지스터
//    reg        r_btn_prev;       // 2. 이전 상태 저장 (엣지 검출용)
//    reg        r_btn_posedge;    // 2. "버튼을 누른 순간" (1-clk 펄스)

//    // --- 버튼 신호 처리 (동기화 + 엣지 검출) ---
//    // 디바운싱(시간 측정) 로직이 빠져있습니다.
//    always @(posedge i_clk or negedge i_rst_n)
//    begin
//        if (i_rst_n == 1'b0) // 리셋
//        begin
//            r_btn_sync    <= 2'b00;
//            r_btn_prev    <= 1'b0;
//            r_btn_posedge <= 1'b0;
//        end
//        else // 클럭 상승 시
//        begin
//            // 1. 동기화: 외부 i_btn 입력을 2단 플립플랍으로 받음
//            r_btn_sync <= {r_btn_sync[0], i_btn};
            
//            // 2. 엣지 검출 (이전 상태 저장)
//            // '디바운싱'된 신호가 아닌 '동기화만 된' 신호(r_btn_sync[1])를 바로 사용
//            r_btn_prev <= r_btn_sync[1]; 
            
//            // 3. 엣지 검출 (펄스 생성)
//            // 이전 상태(r_btn_prev)는 0이고, 현재 상태(r_btn_sync[1])는 1인 순간 감지
//            if (r_btn_sync[1] == 1'b1 && r_btn_prev == 1'b0)
//            begin
//                r_btn_posedge <= 1'b1; // 1클럭 동안 펄스 발생
//            end
//            else
//            begin
//                r_btn_posedge <= 1'b0;
//            end
//        end
//    end
    
//// LED 제어
//always @(posedge i_clk or negedge i_rst_n)
//begin
//    if (i_rst_n == 1'b0)
//        o_led <= 0;
//    else
//    begin
//        if(r_btn_posedge == 1'b1)
//            o_led <= ~o_led;
//    end
//end
//endmodule

//// 버튼 제어하기 1(교수님)
//module week10(
//    input   wire    i_clk,
//    input   wire    i_rst_n,
//    input   wire    i_btn,
//    output  wire     o_led
//);

//// 지연된 버튼 입력
//reg     r_btn_dly;                                             //지연된 버튼
//always @(posedge i_clk or negedge i_rst_n)
//begin
//    if(~i_rst_n)
//        r_btn_dly <= 0;
//    else
//        r_btn_dly <= i_btn;
//end

//// 버튼을 누른 순간
//wire    w_btn_posedge;
////assign  w_btn_posedge = (i_btn == 1) & r_btn_dly == 0);        // i_btn이 1, r_btn_dly 가 0인 부분만 1로 만듬
//assign  w_btn_posedge = i_btn & ~r_btn_dly;                      // 두 코드가 같은 수행을 함

//// LED제어
//reg     r_led;
//always @(posedge i_clk or negedge i_rst_n)
//begin
//    if(~i_rst_n)
//        r_led <= 0;
//    else
//    begin
//        if(w_btn_posedge)
//            r_led <= ~r_led;
//    end
//end
//assign  o_led = r_led;
//endmodule

////버튼 제어하기 2
//module week10(
//    input   wire         i_clk,
//    input   wire         i_rst_n,
//    input   wire         i_btn,
//    output  reg  [6:0]   o_seg,
//    output  wire [7:0]   o_an                                 //segment하나만 사용할때는 따로 선언해주지 않아도됨
//);

//assign o_an = 8'b1111_1110;
//reg     r_btn_dly;                                             //지연된 버튼
//always @(posedge i_clk or negedge i_rst_n)
//begin
//    if(~i_rst_n)
//        r_btn_dly <= 0;
//    else
//        r_btn_dly <= i_btn;
//end

//wire    w_btn_posedge;
////assign  w_btn__posedge = (i_btn == 1) & r_btn_dly == 0);        // i_btn이 1, r_btn_dly 가 0인 부분만 1로 만듬
//assign  w_btn_posedge = i_btn & ~r_btn_dly;                      // 두 코드가 같은 수행을 함

//reg     [3:0]     r_count;
//// 7-segment 제어
//always @(posedge i_clk or negedge i_rst_n)
//begin
//    if (i_rst_n == 0)
//        r_count <= 0;
//    else
//    begin
//        if (w_btn_posedge == 1)
//            if(r_count == 4'd9)
//                r_count <= 4'd0;
//            else
//                r_count <= r_count + 1;
//    end
//end

//// 7-segment 변화제어
//always @(*)
//begin
//    case(r_count)
//        4'd0:    o_seg = 7'b1000000; // '0'
//        4'd1:    o_seg = 7'b1111001; // '1'
//        4'd2:    o_seg = 7'b0100100; // '2'
//        4'd3:    o_seg = 7'b0110000; // '3'
//        4'd4:    o_seg = 7'b0011001; // '4'
//        4'd5:    o_seg = 7'b0010010; // '5'
//        4'd6:    o_seg = 7'b0000010; // '6'
//        4'd7:    o_seg = 7'b1111000; // '7'
//        4'd8:    o_seg = 7'b0000000; // '8'
//        4'd9:    o_seg = 7'b0010000; // '9'
//        default: o_seg = 7'b1111111; // 9보다 큰 값이면 LED를 모두 끔
//    endcase
//end
//endmodule

// 버튼 제어하기 2(교수님)
module week10(
    input    wire            i_clk,
    input    wire            i_rst_n,
    input    wire            i_btn,
    output   wire    [7:0]   o_seg,
    output   wire    [7:0]   o_an
);

//지연된 버튼
assign o_an = 8'b1111_1110;
reg     r_btn_dly;                                             //지연된 버튼
always @(posedge i_clk or negedge i_rst_n)
begin
    if(~i_rst_n)
        r_btn_dly <= 0;
    else
        r_btn_dly <= i_btn;
end

//버튼 상승엣지(버튼 누른 순간)
wire    w_btn_posedge;
//assign  w_btn__posedge = (i_btn == 1) & r_btn_dly == 0);        // i_btn이 1, r_btn_dly 가 0인 부분만 1로 만듬
assign  w_btn_posedge = i_btn & ~r_btn_dly;                      // 두 코드가 같은 수행을 함

// 0~9까지 카운트
reg     [3:0]   r_cnt;
always @(posedge i_clk or negedge i_rst_n)
begin
    if(~i_rst_n)
        r_cnt <= 0;
    else
    begin
        if(w_btn_posedge == 1)
        begin
            if(r_cnt == 9)
                r_cnt <= 0;
            else
                r_cnt <= r_cnt + 1;
        end
    end
end

// 카운트 된 값 seg_decoder에서 결과 가져옴
wire        [6:0]   w_ca;
seg_decoder uut(
    .i_digit    (r_cnt      ),
    .o_ca       (w_ca       )
);
assign  o_seg = {1'b1, w_ca};                               // w_ca의 7비트와 dot을 끄는 1비트를 합쳐 8비트로 만들어 출력
endmodule

FPGA_project/week10/week10.srcs/sim_1/new/week10_tb.v
`timescale 1ns / 1ps
//////////////////////////////////////////////////////////////////////////////////
// Company: 
// Engineer: 
// 
// Create Date: 2025/11/16 13:16:54
// Design Name: 
// Module Name: week10_tb
// Project Name: 
// Target Devices: 
// Tool Versions: 
// Description: 
// 
// Dependencies: 
// 
// Revision:
// Revision 0.01 - File Created
// Additional Comments:
// 
//////////////////////////////////////////////////////////////////////////////////

//// 버튼 제어하기1 테스트 벤치
//module week10_tb;

//reg  i_clk;
//reg  i_rst_n;
//reg  i_btn;
//wire o_led;

//// DUT 인스턴스
//week10 dut (
//    .i_clk   (i_clk),
//    .i_rst_n (i_rst_n),
//    .i_btn   (i_btn),
//    .o_led   (o_led)
//);

//// DUT 내부 신호를 TB에서 바로 보기
//wire btn_dly   = dut.r_btn_dly;       // 지연된 버튼
//wire btn_pe    = dut.w_btn_posedge;   // 버튼 상승엣지 검출

//// 클럭: 10ns 주기
//initial begin
//    i_clk = 0;
//    forever #5 i_clk = ~i_clk;        // 5ns마다 토글 → 10ns period
//end

//// VCD 덤프
//initial begin
//    $dumpfile("week10_tb.vcd");
//    $dumpvars(0, week10_tb);
//end

//// 자극 시나리오
//initial begin
//    i_rst_n = 0;
//    i_btn   = 0;

//    // 리셋 해제 (클럭과 애매하게 어긋나게)
//    #12;
//    i_rst_n = 1;

//    // 조금 기다리기 (클럭 2개)
//    repeat (2) @(posedge i_clk);

//    // ============================
//    // 1번째 버튼: 클럭 중간에 누르고 2클럭 정도 유지
//    // ============================
//    // 현재 posedge에서 2ns 뒤 (클럭 중간쯤) 버튼 올림
//    #2;
//    i_btn = 1;           // 예: t ? 17ns쯤
//    #20;                 // 20ns 유지 → 2클럭 정도
//    i_btn = 0;

//    // 이 때 LED는 1번 토글되어야 한다.

//    // 클럭 3개 기다리기
//    repeat (3) @(posedge i_clk);

//    // ============================
//    // 2번째 버튼: 또 다른 타이밍에서 1.5클럭 정도 유지
//    // ============================
//    #4;
//    i_btn = 1;
//    #15;                 // 1.5클럭 정도
//    i_btn = 0;

//    i_rst_n = 0;
    
    
//    // 조금 기다리기 (클럭 2개)
//    repeat (2) @(posedge i_clk);

//    // ============================
//    // 1번째 버튼: 클럭 중간에 누르고 2클럭 정도 유지
//    // ============================
//    // 현재 posedge에서 2ns 뒤 (클럭 중간쯤) 버튼 올림
//    #2;
//    i_btn = 1;           // 예: t ? 17ns쯤
//    #20;                 // 20ns 유지 → 2클럭 정도
//    i_btn = 0;

//    // 이 때 LED는 1번 토글되어야 한다.

//    // 클럭 3개 기다리기
//    repeat (3) @(posedge i_clk);

//    // ============================
//    // 2번째 버튼: 또 다른 타이밍에서 1.5클럭 정도 유지
//    // ============================
//    #4;
//    i_btn = 1;
//    #15;                 // 1.5클럭 정도
//    i_btn = 0;

//    // 마지막 여유 시간
//    #100;
//    $finish;
//end

//// 매 클럭마다 상태 모니터링
//always @(posedge i_clk) begin
//    $display("[%0t] rst=%0b  btn=%0b  btn_dly=%0b  btn_pe=%0b  led=%0b",
//             $time, i_rst_n, i_btn, btn_dly, btn_pe, o_led);
//end

//endmodule

//// 버튼 제어하기 2 테스트 벤치
//module tb_week10;

//    reg         i_clk;
//    reg         i_rst_n;
//    reg         i_btn;
//    wire [7:0]  o_seg;
//    wire [7:0]  o_an;

//    // DUT
//    week10 dut (
//        .i_clk  (i_clk  ),
//        .i_rst_n(i_rst_n),
//        .i_btn  (i_btn  ),
//        .o_seg  (o_seg  ),
//        .o_an   (o_an   )
//    );

//    // 내부 신호 확인용
//    wire        w_btn_posedge = dut.w_btn_posedge;
//    wire [3:0]  r_cnt         = dut.r_cnt;
//    wire        r_btn_dly     = dut.r_btn_dly;

//    // 클럭 100MHz (10ns 주기)
//    initial begin
//        i_clk = 0;
//        forever #5 i_clk = ~i_clk;
//    end

//    // 버튼 태스크
//    task press_button;
//        input integer pre_delay_ns;   // 버튼을 누르기 전 대기 시간
//        input integer press_width_ns; // 버튼을 누르고 있는 시간
//        begin
//            #(pre_delay_ns);
//            i_btn = 1;
//            #(press_width_ns);
//            i_btn = 0;
//        end
//    endtask

//    initial begin
//        i_rst_n = 0;
//        i_btn   = 0;

//        $dumpfile("week10_tb.vcd");
//        $dumpvars(0, tb_week10);

//        // 초기 리셋
//        #20;
//        i_rst_n = 1;

//        // 첫 번째 카운트 시퀀스 (0~9, 다시 0)
//        // 모든 pre_delay >= 11ns 로 해서 버튼 low 구간마다 클럭 엣지가 최소 1번은 들어가도록 함
//        press_button(12, 17);  // 0 -> 1
//        press_button(13, 19);  // 1 -> 2
//        press_button(15, 13);  // 2 -> 3
//        press_button(11, 22);  // 3 -> 4
//        press_button(18, 15);  // 4 -> 5
//        press_button(13, 17);  // 5 -> 6
//        press_button(16, 14);  // 6 -> 7
//        press_button(11, 21);  // 7 -> 8
//        press_button(15, 18);  // 8 -> 9
//        press_button(12, 13);  // 9 -> 0

//        // 추가로 몇 번 더 눌러서 0,1,2,... 로 계속 도는 것도 확인
//        press_button(14, 16);  // 0 -> 1
//        press_button(11, 20);  // 1 -> 2

//        #100;

//        // 두 번째 리셋
//        i_rst_n = 0;

//        // 두 번째 카운트 시퀀스 (다른 타이밍 패턴)
//        press_button(13, 18);  // 0 -> 1
//        press_button(16, 14);  // 1 -> 2
//        press_button(11, 23);  // 2 -> 3
//        press_button(19, 15);  // 3 -> 4
//        press_button(12, 19);  // 4 -> 5
//        press_button(17, 13);  // 5 -> 6
//        press_button(11, 21);  // 6 -> 7
//        press_button(14, 16);  // 7 -> 8
//        press_button(18, 15);  // 8 -> 9
//        press_button(11, 22);  // 9 -> 0

//        press_button(15, 17);  // 0 -> 1
//        press_button(12, 18);  // 1 -> 2

//        #100;
//        $finish;
//    end

//endmodule

module tb_week10;

    reg         i_clk;
    reg         i_rst_n;
    reg         i_btn;
    wire [7:0]  o_seg;
    wire [7:0]  o_an;

    // DUT
    week10 dut (
        .i_clk   (i_clk),
        .i_rst_n (i_rst_n),
        .i_btn   (i_btn),
        .o_seg   (o_seg),
        .o_an    (o_an)
    );

    // 100 MHz 클럭 (10 ns)
    initial begin
        i_clk = 0;
        forever #5 i_clk = ~i_clk;
    end

    initial begin
        // 초기값
        i_rst_n = 0;
        i_btn   = 0;

        // 리셋 해제
        #100;
        i_rst_n = 1;

        // --- 1번째 버튼 눌림 : 바운싱 구간 ---
        #500;
        repeat(10) begin
            #40;
            i_btn = ~i_btn;    // 0/1 빠르게 토글 → 바운싱 흉내
        end

        // 안정적으로 HIGH 유지 (진짜 눌린 상태)
        i_btn = 1;
        #500;

        // --- 1번째 버튼 뗌 : 바운싱 구간 ---
        repeat(10) begin
            #40;
            i_btn = ~i_btn;
        end

        // 안정적으로 LOW 유지 (완전히 뗀 상태)
        i_btn = 0;
        #100_0;

        // 시뮬레이션 종료
        #1000;
        $finish;
    end

    // 파형 확인용 (필요 없으면 이것도 지워도 됨)
    initial begin
        $dumpfile("week10_tb.vcd");
        $dumpvars(0, tb_week10);
    end

endmodule

FPGA_project/week10/week10.sim/sim_1/behav/xsim/week10_tb.vcd
$date
   Sun Nov 23 10:06:48 2025
$end
$version
  2022.1
$end
$timescale
  1ps
$end
$scope module tb_week10 $end
$var reg 1 ! i_clk $end
$var reg 1 " i_rst_n $end
$var reg 1 # i_btn $end
$var wire 8 $ o_seg [7:0] $end
$var wire 8 % o_an [7:0] $end
$scope module dut $end
$var wire 1 & i_clk $end
$var wire 1 ' i_rst_n $end
$var wire 1 ( i_btn $end
$var wire 8 $ o_seg [7:0] $end
$var wire 8 % o_an [7:0] $end
$var reg 1 ) r_btn_dly $end
$var wire 1 * w_btn_posedge $end
$var reg 4 + r_cnt [3:0] $end
$var wire 7 , w_ca [6:0] $end
$scope module uut $end
$var wire 4 - i_digit [3:0] $end
$var reg 7 . o_ca [6:0] $end
$upscope $end
$upscope $end
$upscope $end
$enddefinitions $end
#0
$dumpvars
0!
0"
0#
b11000000 $
b11111110 %
0&
0'
0(
0)
0*
b0 +
b1000000 ,
b0 -
b1000000 .
$end
#5000
1!
1&
#10000
0!
0&
#15000
1!
1&
#20000
0!
0&
#25000
1!
1&
#30000
0!
0&
#35000
1!
1&
#40000
0!
0&
#45000
1!
1&
#50000
0!
0&
#55000
1!
1&
#60000
0!
0&
#65000
1!
1&
#70000
0!
0&
#75000
1!
1&
#80000
0!
0&
#85000
1!
1&
#90000
0!
0&
#95000
1!
1&
#100000
0!
1"
0&
1'
#105000
1!
1&
#110000
0!
0&
#115000
1!
1&
#120000
0!
0&
#125000
1!
1&
#130000
0!
0&
#135000
1!
1&
#140000
0!
0&
#145000
1!
1&
#150000
0!
0&
#155000
1!
1&
#160000
0!
0&
#165000
1!
1&
#170000
0!
0&
#175000
1!
1&
#180000
0!
0&
#185000
1!
1&
#190000
0!
0&
#195000
1!
1&
#200000
0!
0&
#205000
1!
1&
#210000
0!
0&
#215000
1!
1&
#220000
0!
0&
#225000
1!
1&
#230000
0!
0&
#235000
1!
1&
#240000
0!
0&
#245000
1!
1&
#250000
0!
0&
#255000
1!
1&
#260000
0!
0&
#265000
1!
1&
#270000
0!
0&
#275000
1!
1&
#280000
0!
0&
#285000
1!
1&
#290000
0!
0&
#295000
1!
1&
#300000
0!
0&
#305000
1!
1&
#310000
0!
0&
#315000
1!
1&
#320000
0!
0&
#325000
1!
1&
#330000
0!
0&
#335000
1!
1&
#340000
0!
0&
#345000
1!
1&
#350000
0!
0&
#355000
1!
1&
#360000
0!
0&
#365000
1!
1&
#370000
0!
0&
#375000
1!
1&
#380000
0!
0&
#385000
1!
1&
#390000
0!
0&
#395000
1!
1&
#400000
0!
0&
#405000
1!
1&
#410000
0!
0&
#415000
1!
1&
#420000
0!
0&
#425000
1!
1&
#430000
0!
0&
#435000
1!
1&
#440000
0!
0&
#445000
1!
1&
#450000
0!
0&
#455000
1!
1&
#460000
0!
0&
#465000
1!
1&
#470000
0!
0&
#475000
1!
1&
#480000
0!
0&
#485000
1!
1&
#490000
0!
0&
#495000
1!
1&
#500000
0!
0&
#505000
1!
1&
#510000
0!
0&
#515000
1!
1&
#520000
0!
0&
#525000
1!
1&
#530000
0!
0&
#535000
1!
1&
#540000
0!
0&
#545000
1!
1&
#550000
0!
0&
#555000
1!
1&
#560000
0!
0&
#565000
1!
1&
#570000
0!
0&
#575000
1!
1&
#580000
0!
0&
#585000
1!
1&
#590000
0!
0&
#595000
1!
1&
#600000
0!
0&
#605000
1!
1&
#610000
0!
0&
#615000
1!
1&
#620000
0!
0&
#625000
1!
1&
#630000
0!
0&
#635000
1!
1&
#640000
0!
1#
0&
1(
1*
#645000
1!
b11111001 $
1&
1)
0*
b1 +
b1111001 ,
b1 -
b1111001 .
#650000
0!
0&
#655000
1!
1&
#660000
0!
0&
#665000
1!
1&
#670000
0!
0&
#675000
1!
1&
#680000
0!
0#
0&
0(
#685000
1!
1&
0)
#690000
0!
0&
#695000
1!
1&
#700000
0!
0&
#705000
1!
1&
#710000
0!
0&
#715000
1!
1&
#720000
0!
1#
0&
1(
1*
#725000
1!
b10100100 $
1&
1)
0*
b10 +
b100100 ,
b10 -
b100100 .
#730000
0!
0&
#735000
1!
1&
#740000
0!
0&
#745000
1!
1&
#750000
0!
0&
#755000
1!
1&
#760000
0!
0#
0&
0(
#765000
1!
1&
0)
#770000
0!
0&
#775000
1!
1&
#780000
0!
0&
#785000
1!
1&
#790000
0!
0&
#795000
1!
1&
#800000
0!
1#
0&
1(
1*
#805000
1!
b10110000 $
1&
1)
0*
b11 +
b110000 ,
b11 -
b110000 .
#810000
0!
0&
#815000
1!
1&
#820000
0!
0&
#825000
1!
1&
#830000
0!
0&
#835000
1!
1&
#840000
0!
0#
0&
0(
#845000
1!
1&
0)
#850000
0!
0&
#855000
1!
1&
#860000
0!
0&
#865000
1!
1&
#870000
0!
0&
#875000
1!
1&
#880000
0!
1#
0&
1(
1*
#885000
1!
b10011001 $
1&
1)
0*
b100 +
b11001 ,
b100 -
b11001 .
#890000
0!
0&
#895000
1!
1&
#900000
0!
0&
#905000
1!
1&
#910000
0!
0&
#915000
1!
1&
#920000
0!
0#
0&
0(
#925000
1!
1&
0)
#930000
0!
0&
#935000
1!
1&
#940000
0!
0&
#945000
1!
1&
#950000
0!
0&
#955000
1!
1&
#960000
0!
1#
0&
1(
1*
#965000
1!
b10010010 $
1&
1)
0*
b101 +
b10010 ,
b101 -
b10010 .
#970000
0!
0&
#975000
1!
1&
#980000
0!
0&
#985000
1!
1&
#990000
0!
0&
#995000
1!
1&
#1000000
0!
1#
0&
1(
